efmloader/__init__.py
efmloader/loader.py
efmloader-0.1.0.dist-info/METADATA
efmloader-0.1.0.dist-info/WHEEL
efmloader-0.1.0.dist-info/top_level.txt
efmloader-0.1.0.dist-info/RECORD
